envdot/__init__.py
envdot/auto_detect_example.py
envdot/core.py
envdot/custom_logging.py
envdot/exceptions.py
envdot/helpers.py
envdot-1.0.29.dist-info/licenses/LICENSE
envdot-1.0.29.dist-info/METADATA
envdot-1.0.29.dist-info/WHEEL
envdot-1.0.29.dist-info/top_level.txt
envdot-1.0.29.dist-info/RECORD
