Metadata-Version: 2.4
Name: envdot
Version: 1.0.29
Summary: Enhanced environment variable management with multi-format support (.env, JSON, YAML, INI, TOML)
Home-page: https://github.com/cumulus13/envdot
Author: Hadi Cahyadi
Author-email: Hadi Cahyadi <cumulus13@gmail.com>
Maintainer-email: Hadi Cahyadi <cumulus13@gmail.com>
License-Expression: MIT
Project-URL: Homepage, https://github.com/cumulus13/envdot
Project-URL: Documentation, https://envdot.readthedocs.io
Project-URL: Repository, https://github.com/cumulus13/envdot
Project-URL: Bug Tracker, https://github.com/cumulus13/envdot/issues
Keywords: environment,config,configuration,env,dotenv,yaml,json,toml,ini,settings
Classifier: Development Status :: 5 - Production/Stable
Classifier: Intended Audience :: Developers
Classifier: Operating System :: OS Independent
Classifier: Programming Language :: Python :: 3
Classifier: Programming Language :: Python :: 3.8
Classifier: Programming Language :: Python :: 3.9
Classifier: Programming Language :: Python :: 3.10
Classifier: Programming Language :: Python :: 3.11
Classifier: Programming Language :: Python :: 3.12
Classifier: Topic :: Software Development :: Libraries :: Python Modules
Classifier: Topic :: System :: Systems Administration
Classifier: Topic :: Utilities
Requires-Python: >=3.8
License-File: LICENSE
Requires-Dist: version_get
Provides-Extra: full
Requires-Dist: pyyaml>=6.0.1; extra == "full"
Requires-Dist: tomli>=2.0.1; python_version < "3.11" and extra == "full"
Requires-Dist: tomli-w>=1.0.0; extra == "full"
Requires-Dist: json5>=0.9.14; extra == "full"
Requires-Dist: richcolorlog>=0.1.0; extra == "full"
Provides-Extra: yaml
Requires-Dist: pyyaml>=6.0.1; extra == "yaml"
Provides-Extra: toml
Requires-Dist: tomli>=2.0.1; python_version < "3.11" and extra == "toml"
Requires-Dist: tomli-w>=1.0.0; extra == "toml"
Provides-Extra: json5
Requires-Dist: json5>=0.9.14; extra == "json5"
Provides-Extra: rich
Requires-Dist: richcolorlog>=0.1.0; extra == "rich"
Provides-Extra: dev
Requires-Dist: pytest>=7.4.0; extra == "dev"
Requires-Dist: pytest-cov>=4.1.0; extra == "dev"
Requires-Dist: black>=23.0.0; extra == "dev"
Requires-Dist: flake8>=6.0.0; extra == "dev"
Requires-Dist: mypy>=1.5.0; extra == "dev"
Requires-Dist: pre-commit>=3.3.0; extra == "dev"
Dynamic: author
Dynamic: home-page
Dynamic: license-file
Dynamic: requires-python
